multienv/__init__.py
multienv/pyenvs.py
multienv/pyenvs_deps.py
multienv/pyenvs_deps_formatter.py
multienv/pyenvs_deps_input_std.py
multienv/pyenvs_deps_output_conda.py
multienv/pyenvs_deps_output_pip.py
multienv/pyenvs_lint.py
multienv/pyenvs_lint_formatter.py
multienv/pyenvs_lint_input_std.py
multienv/pyenvs_lint_output_pylint.py
multienv-0.5.0.dist-info/LICENSE.md
multienv-0.5.0.dist-info/METADATA
multienv-0.5.0.dist-info/WHEEL
multienv-0.5.0.dist-info/entry_points.txt
multienv-0.5.0.dist-info/top_level.txt
multienv-0.5.0.dist-info/RECORD
