Metadata-Version: 2.1
Name: multienv
Version: 0.5.0
Author-email: Samuel Andrés <samuel.andres@yahoo.fr>
License: This is free and unencumbered software released into the public domain.
Project-URL: Homepage, https://github.com/SamuelAndresPascal/cosmoloj-py/tree/multienv_0.5.0/multienv
Project-URL: Documentation, http://cosmoloj.com/mkdocs/multienv/0.5.0
Classifier: Programming Language :: Python :: 3
Classifier: Operating System :: OS Independent
Classifier: Development Status :: 5 - Production/Stable
Classifier: Intended Audience :: Developers
Classifier: License :: Public Domain
Classifier: Topic :: Software Development
Classifier: Topic :: Utilities
Requires-Python: >=3.12
License-File: LICENSE.md
Requires-Dist: pyyaml >=6
